esc3/pc.v
`timescale 1ns/1ps

module PC(
    input  wire        clk,
    input  wire        reset,
    input  wire        load,
    input  wire        inc,
    input  wire [15:0] in,
    output reg  [15:0] out
);
    initial out = 16'h0000;

    always @(posedge clk) begin
        if (reset) begin
            out <= 16'h0000;
        end else if (load) begin
            out <= in;
        end else if (inc) begin
            out <= out + 16'h0001;
        end
    end
endmodule

esc2_alu/alu.v
module alu(
    input [15:0] x,
    input [15:0] y,
    input zx,
    input nx,
    input zy,
    input ny,
    input f,
    input no,
    output [15:0] out,
    output zr,
    output ng
);
    wire [15:0] zx_out, nx_out, zy_out, ny_out, f_out, no_out;
    
    assign zx_out = zx ? 16'b0 : x;
    assign nx_out = nx ? ~zx_out : zx_out;
    
    assign zy_out = zy ? 16'b0 : y;
    assign ny_out = ny ? ~zy_out : zy_out;
    
    assign f_out = f ? (nx_out + ny_out) : (nx_out & ny_out);
    assign no_out = no ? ~f_out : f_out;
    
    assign out = no_out;
    assign zr = (no_out == 16'b0) ? 1'b1 : 1'b0;
    assign ng = no_out[15];
endmodule

T5_JoaoEmanuel/esc5/CPU.v
`timescale 1ns/1ps

/*
 * CPU Module - Hack Computer Central Processing Unit
 * 
 * The Hack CPU executes 16-bit instructions with the following format:
 * 
 * A-instruction (bit 15 = 0): 0vvvvvvvvvvvvvvv
 *   - Loads value vvvvvvvvvvvvvvv into A register
 * 
 * C-instruction (bit 15 = 1): 111a cccccc ddd jjj
 *   - a:      A/M select (0=A, 1=M[A])
 *   - cccccc: ALU control bits (zx, nx, zy, ny, f, no)
 *   - ddd:    Destination (A, D, M)
 *   - jjj:    Jump condition
 * 
 * Inputs:
 *   - inM:         Memory input (M[A])
 *   - instruction: Current instruction to execute
 *   - reset:       Reset PC to 0
 * 
 * Outputs:
 *   - outM:      Memory output (to be written to M[A])
 *   - writeM:    Memory write enable
 *   - addressM:  Memory address (A register)
 *   - pc:        Program counter
 */

module CPU(
    input  wire         clk,
    input  wire         reset,
    input  wire [15:0]  inM,          // M value input (data from memory)
    input  wire [15:0]  instruction,  // Instruction for execution
    output wire [15:0]  outM,         // M value output (data to memory)
    output wire         writeM,       // Write to M?
    output wire [14:0]  addressM,     // Address in data memory (of M)
    output wire [14:0]  pc            // Address of next instruction
);

    // Internal registers
    reg  [15:0] A;      // A register
    reg  [15:0] D;      // D register
    wire [15:0] PC_out; // Program Counter output (16-bit internally)
    
    // Instruction decode
    wire is_c_inst;     // Is C-instruction?
    wire is_a_inst;     // Is A-instruction?
    
    wire a_bit;         // A/M select
    wire [5:0] comp;    // Compute bits
    wire [2:0] dest;    // Destination bits
    wire [2:0] jump;    // Jump bits
    
    // ALU signals
    wire [15:0] alu_x, alu_y, alu_out;
    wire alu_zr, alu_ng;
    
    // Control signals
    wire load_a, load_d, load_pc;
    wire do_jump;
    wire inc_pc;
    
    // Instruction type
    assign is_c_inst = instruction[15];
    assign is_a_inst = ~instruction[15];
    
    // Decode C-instruction fields
    assign a_bit = instruction[12];
    assign comp  = instruction[11:6];  // ALU control: zx, nx, zy, ny, f, no
    assign dest  = instruction[5:3];   // d1=A, d2=D, d3=M
    assign jump  = instruction[2:0];   // j1=<0, j2==0, j3=>0
    
    // ALU inputs
    assign alu_x = D;                           // X is always D register
    assign alu_y = a_bit ? inM : A;             // Y is A or M[A] depending on a-bit
    
    // ALU instance
    alu alu_inst(
        .x(alu_x),
        .y(alu_y),
        .zx(comp[5]),
        .nx(comp[4]),
        .zy(comp[3]),
        .ny(comp[2]),
        .f(comp[1]),
        .no(comp[0]),
        .out(alu_out),
        .zr(alu_zr),
        .ng(alu_ng)
    );
    
    // Control logic for A register
    // Load A if: (1) A-instruction, or (2) C-instruction with dest[2] (d1) set
    assign load_a = is_a_inst | (is_c_inst & dest[2]);
    
    // A register
    always @(posedge clk) begin
        if (reset) begin
            A <= 16'h0000;
        end else if (load_a) begin
            if (is_a_inst)
                A <= instruction;  // A-instruction: load value
            else
                A <= alu_out;      // C-instruction: load ALU output
        end
    end
    
    // Control logic for D register
    // Load D if: C-instruction with dest[1] (d2) set
    assign load_d = is_c_inst & dest[1];
    
    // D register
    always @(posedge clk) begin
        if (reset) begin
            D <= 16'h0000;
        end else if (load_d) begin
            D <= alu_out;
        end
    end
    
    // Jump logic
    // Determine if we should jump based on ALU flags and jump bits
    wire jlt, jeq, jgt;
    assign jlt = jump[2] & alu_ng;         // j1: jump if < 0
    assign jeq = jump[1] & alu_zr;         // j2: jump if == 0
    assign jgt = jump[0] & (~alu_ng & ~alu_zr);  // j3: jump if > 0
    
    assign do_jump = is_c_inst & (jlt | jeq | jgt);
    assign inc_pc = ~do_jump;
    assign load_pc = do_jump;
    
    // Program Counter
    PC pc_inst(
        .clk(clk),
        .reset(reset),
        .load(load_pc),
        .inc(inc_pc),
        .in(A),
        .out(PC_out)
    );
    
    // Outputs
    assign outM = alu_out;                      // Data to write to memory
    assign writeM = is_c_inst & dest[0];        // Write to M if C-instruction with dest[0] (d3) set
    assign addressM = A[14:0];                  // Memory address from A register
    assign pc = PC_out[14:0];                   // Program counter (15-bit address)

endmodule

T5_JoaoEmanuel/esc5/tb_CPU.v
`timescale 1ns/1ps

/*
 * Test Bench for CPU Module
 * 
 * Tests basic CPU operations with simple instructions.
 */

module tb_CPU;

    // Clock and reset
    reg         clk;
    reg         reset;
    
    // CPU signals
    reg  [15:0] inM;
    reg  [15:0] instruction;
    wire [15:0] outM;
    wire        writeM;
    wire [14:0] addressM;
    wire [14:0] pc;
    
    // Instantiate CPU
    CPU uut(
        .clk(clk),
        .reset(reset),
        .inM(inM),
        .instruction(instruction),
        .outM(outM),
        .writeM(writeM),
        .addressM(addressM),
        .pc(pc)
    );
    
    // Clock generation (10ns period)
    initial clk = 0;
    always #5 clk = ~clk;
    
    // Test stimulus
    initial begin
        $dumpfile("tb_cpu.vcd");
        $dumpvars(0, tb_CPU);
        
        $display("===== CPU Test Starting =====");
        
        // Initialize
        reset = 1;
        inM = 0;
        instruction = 0;
        
        // Release reset after 2 cycles
        #20;
        reset = 0;
        
        // Test 1: A-instruction (@5)
        #10;
        $display("Test 1: A-instruction @5");
        instruction = 16'b0000000000000101;  // @5
        #10;
        if (addressM == 15'd5)
            $display("  PASS: A register = %d", addressM);
        else
            $display("  FAIL: Expected A=5, got A=%d", addressM);
        
        // Test 2: C-instruction (D=A)
        #10;
        $display("Test 2: C-instruction D=A");
        instruction = 16'b1110110000010000;  // D=A
        #10;
        $display("  INFO: D register loaded from A");
        
        // Test 3: A-instruction (@10)
        #10;
        $display("Test 3: A-instruction @10");
        instruction = 16'b0000000000001010;  // @10
        #10;
        if (addressM == 15'd10)
            $display("  PASS: A register = %d", addressM);
        else
            $display("  FAIL: Expected A=10, got A=%d", addressM);
        
        // Test 4: C-instruction (D=D+A, should be 5+10=15)
        $display("Test 4: C-instruction D=D+A");
        instruction = 16'b1110000010010000;  // D=D+A
        #10;
        $display("  INFO: D = D + A (should be 15)");
        
        // Test 5: A-instruction to set address for memory write
        $display("Test 5a: Setting address @10 for memory write");
        instruction = 16'b0000000000001010;  // @10
        #10;
        
        // Test 5b: C-instruction (M=D, write to memory)
        $display("Test 5b: C-instruction M=D");
        instruction = 16'b1110001100001000;  // M=D
        #10;
        if (writeM && outM == 16'd15)
            $display("  PASS: Writing %d to memory at address %d", outM, addressM);
        else
            $display("  FAIL: Expected writeM=1, outM=15, got writeM=%d, outM=%d", writeM, outM);
        
        // Test 6: Unconditional jump (@0; 0;JMP)
        #10;
        $display("Test 6: Testing jump");
        instruction = 16'b0000000000000000;  // @0
        #10;
        instruction = 16'b1110101010000111;  // 0;JMP
        #10;
        if (pc == 15'd0)
            $display("  PASS: PC jumped to 0");
        else
            $display("  FAIL: Expected PC=0, got PC=%d", pc);
        
        #50;
        $display("===== CPU Test Complete =====");
        $finish;
    end

endmodule

T5_JoaoEmanuel/esc5/tb_cpu.vcd
$date
	Sat Feb 14 12:37:02 2026
$end
$version
	Icarus Verilog
$end
$timescale
	1ps
$end
$scope module tb_CPU $end
$var wire 1 ! writeM $end
$var wire 15 " pc [14:0] $end
$var wire 16 # outM [15:0] $end
$var wire 15 $ addressM [14:0] $end
$var reg 1 % clk $end
$var reg 16 & inM [15:0] $end
$var reg 16 ' instruction [15:0] $end
$var reg 1 ( reset $end
$scope module uut $end
$var wire 16 ) alu_x [15:0] $end
$var wire 1 % clk $end
$var wire 1 * do_jump $end
$var wire 16 + inM [15:0] $end
$var wire 1 , inc_pc $end
$var wire 16 - instruction [15:0] $end
$var wire 1 . is_a_inst $end
$var wire 1 / jeq $end
$var wire 1 0 jgt $end
$var wire 1 1 jlt $end
$var wire 1 2 load_a $end
$var wire 1 3 load_d $end
$var wire 1 4 load_pc $end
$var wire 16 5 outM [15:0] $end
$var wire 1 ( reset $end
$var wire 1 ! writeM $end
$var wire 15 6 pc [14:0] $end
$var wire 3 7 jump [2:0] $end
$var wire 1 8 is_c_inst $end
$var wire 3 9 dest [2:0] $end
$var wire 6 : comp [5:0] $end
$var wire 1 ; alu_zr $end
$var wire 16 < alu_y [15:0] $end
$var wire 16 = alu_out [15:0] $end
$var wire 1 > alu_ng $end
$var wire 15 ? addressM [14:0] $end
$var wire 1 @ a_bit $end
$var wire 16 A PC_out [15:0] $end
$var reg 16 B A [15:0] $end
$var reg 16 C D [15:0] $end
$scope module alu_inst $end
$var wire 1 D f $end
$var wire 1 E no $end
$var wire 1 F nx $end
$var wire 1 G ny $end
$var wire 16 H out [15:0] $end
$var wire 16 I x [15:0] $end
$var wire 16 J y [15:0] $end
$var wire 1 K zx $end
$var wire 1 L zy $end
$var wire 16 M zy_out [15:0] $end
$var wire 16 N zx_out [15:0] $end
$var wire 1 ; zr $end
$var wire 16 O ny_out [15:0] $end
$var wire 16 P nx_out [15:0] $end
$var wire 16 Q no_out [15:0] $end
$var wire 1 > ng $end
$var wire 16 R f_out [15:0] $end
$upscope $end
$scope module pc_inst $end
$var wire 1 % clk $end
$var wire 16 S in [15:0] $end
$var wire 1 , inc $end
$var wire 1 4 load $end
$var wire 1 ( reset $end
$var reg 16 T out [15:0] $end
$upscope $end
$upscope $end
$upscope $end
$enddefinitions $end
$comment Show the parameter values. $end
$dumpall
$end
#0
$dumpvars
b0 T
bx S
bx R
bx Q
bx P
bx O
bx N
bx M
0L
0K
bx J
bx I
bx H
0G
0F
0E
0D
bx C
bx B
b0 A
0@
bx ?
x>
bx =
bx <
x;
b0 :
b0 9
08
b0 7
b0 6
bx 5
04
03
12
01
00
0/
1.
b0 -
1,
b0 +
0*
bx )
1(
b0 '
b0 &
0%
bx $
bx #
b0 "
0!
$end
#5000
1;
0>
b0 #
b0 5
b0 =
b0 H
b0 Q
b0 R
b0 O
b0 M
b0 P
b0 <
b0 J
b0 $
b0 ?
b0 N
b0 B
b0 S
b0 )
b0 C
b0 I
1%
#10000
0%
#15000
1%
#20000
0%
0(
#25000
b1 "
b1 6
b1 A
b1 T
1%
#30000
b101 7
0%
b101 '
b101 -
#35000
b101 O
b101 M
b101 <
b101 J
b101 $
b101 ?
b10 "
b10 6
b101 B
b101 S
b10 A
b10 T
1%
#40000
0%
#45000
b11 "
b11 6
b11 A
b11 T
1%
#50000
0;
b101 #
b101 5
b101 =
b101 H
b101 Q
b101 R
02
b1111111111111111 P
13
0.
1K
1F
18
b110000 :
b10 9
b0 7
0%
b1110110000010000 '
b1110110000010000 -
#55000
b100 "
b100 6
b101 )
b101 C
b101 I
b100 A
b100 T
1%
#60000
0%
#65000
b101 "
b101 6
b101 A
b101 T
1%
#70000
0/
0;
b101 #
b101 5
b101 =
b101 H
b101 Q
b101 R
12
b101 N
b101 P
03
1.
0K
0F
08
b0 :
b1 9
b10 7
0%
b1010 '
b1010 -
#75000
1/
1;
b0 #
b0 5
b0 =
b0 H
b0 Q
b0 R
b1010 O
b1010 M
b1010 <
b1010 J
b1010 $
b1010 ?
b110 "
b110 6
b1010 B
b1010 S
b110 A
b110 T
1%
#80000
0;
b1111 #
b1111 5
b1111 =
b1111 H
b1111 Q
1,
02
b1111 R
0/
04
0*
13
0.
1D
18
b10 :
b10 9
b0 7
0%
b1110000010010000 '
b1110000010010000 -
#85000
b11001 #
b11001 5
b11001 =
b11001 H
b11001 Q
b11001 R
b1111 P
b111 "
b111 6
b1111 N
b111 A
b111 T
b1111 )
b1111 C
b1111 I
1%
#90000
b1010 #
b1010 5
b1010 =
b1010 H
b1010 Q
12
b1010 R
03
1.
0D
08
b0 :
b1 9
b10 7
0%
b1010 '
b1010 -
#95000
b1000 "
b1000 6
b1000 A
b1000 T
1%
#100000
b1111 #
b1111 5
b1111 =
b1111 H
b1111 Q
b1111 R
02
b0 M
b1111111111111111 O
1!
0.
1L
1G
18
b1100 :
b0 7
0%
b1110001100001000 '
b1110001100001000 -
#105000
b1001 "
b1001 6
b1001 A
b1001 T
1%
#110000
0%
#115000
b1010 "
b1010 6
b1010 A
b1010 T
1%
#120000
0;
b1010 #
b1010 5
b1010 =
b1010 H
b1010 Q
b1010 R
12
b1010 M
b1010 O
0!
1.
0L
0G
08
b0 :
b0 9
0%
b0 '
b0 -
#125000
1;
b0 #
b0 5
b0 =
b0 H
b0 Q
b0 R
b0 O
b0 M
b1011 "
b1011 6
b0 <
b0 J
b0 $
b0 ?
b1011 A
b1011 T
b0 B
b0 S
1%
#130000
00
0,
14
1*
1;
b0 P
b0 #
b0 5
b0 =
b0 H
b0 Q
02
b0 N
b0 R
1/
0.
1K
1L
1D
18
b101010 :
b111 7
0%
b1110101010000111 '
b1110101010000111 -
#135000
b0 "
b0 6
b0 A
b0 T
1%
