T5_JoaoEmanuel/esc5/Computer.v
`timescale 1ns/1ps

/*
 * Computer Module - Complete Hack Computer System
 * 
 * Integrates:
 *   - CPU: Central Processing Unit
 *   - Memory: Data memory (RAM + Screen + Keyboard)
 *   - ROM32K: Instruction memory (program)
 * 
 * The computer can be reset using the reset signal.
 * When reset is released, the CPU begins executing instructions from address 0.
 */

module Computer(
    input  wire clk,
    input  wire reset
);

    // Internal signals
    wire [15:0] instruction;    // Current instruction from ROM
    wire [15:0] inM;            // Data from memory to CPU
    wire [15:0] outM;           // Data from CPU to memory
    wire [14:0] addressM;       // Data memory address
    wire [14:0] pc;             // Program counter
    wire        writeM;         // Memory write enable
    
    // CPU instance
    CPU cpu(
        .clk(clk),
        .reset(reset),
        .inM(inM),
        .instruction(instruction),
        .outM(outM),
        .writeM(writeM),
        .addressM(addressM),
        .pc(pc)
    );
    
    // Memory instance
    Memory memory(
        .clk(clk),
        .load(writeM),
        .address(addressM),
        .in(outM),
        .out(inM)
    );
    
    // ROM32K instance (instruction memory)
    ROM32K rom(
        .address(pc),
        .out(instruction)
    );

endmodule


/*
 * ROM32K Module - 32K words of read-only instruction memory
 * 
 * This module stores the program to be executed.
 * In simulation, the program is loaded from the testbench.
 */
module ROM32K(
    input  wire [14:0]  address,      // 15-bit address (32K words)
    output wire [15:0]  out           // Instruction output
);
    localparam integer DEPTH = 32768;  // 32K words
    
    reg [15:0] mem [0:DEPTH-1];
    integer idx;
    
    // Initialize memory to NOPs (0x0000 = @0)
    initial begin
        for (idx = 0; idx < DEPTH; idx = idx + 1) begin
            mem[idx] = 16'h0000;
        end
    end
    
    assign out = (address < DEPTH) ? mem[address] : 16'h0000;

endmodule

T5_JoaoEmanuel/esc5/Memory.v
`timescale 1ns/1ps

/*
 * Memory Module - Hack Computer Memory System
 * 
 * Memory map:
 * 0x0000 - 0x3FFF (0-16383):     RAM16K (16K words of general-purpose RAM)
 * 0x4000 - 0x5FFF (16384-24575): Screen memory map (8K words = 256 rows x 512 pixels)
 * 0x6000 (24576):                Keyboard memory map (1 word)
 * 
 * The chip has a 15-bit address input (0-32767), but only addresses 0-24576 are used.
 */

module Memory(
    input  wire         clk,
    input  wire         load,         // Write enable
    input  wire [14:0]  address,      // 15-bit address (32K address space)
    input  wire [15:0]  in,          // Data input
    output reg  [15:0]  out          // Data output
);

    // Internal memory components
    wire [15:0] ram_out, screen_out;
    reg  [15:0] keyboard_reg;
    
    // Control signals
    wire load_ram, load_screen;
    wire sel_ram, sel_screen, sel_keyboard;
    
    // Address decoding
    // RAM:      0x0000 - 0x3FFF (address[14] = 0, address[13] = 0)
    // Screen:   0x4000 - 0x5FFF (address[14] = 1, address[13] = 0)
    // Keyboard: 0x6000          (address[14] = 1, address[13] = 1)
    
    assign sel_ram      = (~address[14]);                      // address < 16384
    assign sel_screen   = (address[14] & ~address[13]);        // 16384 <= address < 24576
    assign sel_keyboard = (address[14] & address[13]);         // address >= 24576
    
    assign load_ram     = load & sel_ram;
    assign load_screen  = load & sel_screen;
    
    // RAM16K instance (addresses 0-16383)
    RAM16K ram(
        .clk(clk),
        .load(load_ram),
        .address(address[13:0]),
        .in(in),
        .out(ram_out)
    );
    
    // Screen memory (8K words, addresses 16384-24575)
    Screen screen(
        .clk(clk),
        .load(load_screen),
        .address(address[12:0]),   // 13-bit address for 8K
        .in(in),
        .out(screen_out)
    );
    
    // Keyboard register (read-only at address 24576)
    // In simulation, this will be set by the testbench
    initial keyboard_reg = 16'h0000;
    
    // Output multiplexing
    always @(*) begin
        case ({sel_keyboard, sel_screen, sel_ram})
            3'b001: out = ram_out;
            3'b010: out = screen_out;
            3'b100: out = keyboard_reg;
            default: out = 16'h0000;
        endcase
    end

endmodule


/*
 * Screen Module - 8K words (256 rows x 512 pixels / 16 pixels per word)
 * Memory-mapped screen buffer
 */
module Screen(
    input  wire         clk,
    input  wire         load,
    input  wire [12:0]  address,      // 13-bit address (8K words)
    input  wire [15:0]  in,
    output wire [15:0]  out
);
    localparam integer DEPTH = 8192;  // 8K words
    
    reg [15:0] mem [0:DEPTH-1];
    integer idx;
    
    initial begin
        for (idx = 0; idx < DEPTH; idx = idx + 1) begin
            mem[idx] = 16'h0000;
        end
    end
    
    always @(posedge clk) begin
        if (load && address < DEPTH) begin
            mem[address] <= in;
        end
    end
    
    assign out = (address < DEPTH) ? mem[address] : 16'h0000;
endmodule

esc3/ram16k.v
`timescale 1ns/1ps

module RAM16K(
    input  wire         clk,
    input  wire         load,
    input  wire [13:0]  address,
    input  wire [15:0]  in,
    output wire [15:0]  out
);
    localparam integer DEPTH = 16384;

    reg [15:0] mem [0:DEPTH-1];
    integer idx;

    initial begin
        for (idx = 0; idx < DEPTH; idx = idx + 1) begin
            mem[idx] = 16'h0000;
        end
    end

    always @(posedge clk) begin
        if (load) begin
            mem[address] <= in;
        end
    end

    assign out = mem[address];
endmodule

esc3/pc.v
`timescale 1ns/1ps

module PC(
    input  wire        clk,
    input  wire        reset,
    input  wire        load,
    input  wire        inc,
    input  wire [15:0] in,
    output reg  [15:0] out
);
    initial out = 16'h0000;

    always @(posedge clk) begin
        if (reset) begin
            out <= 16'h0000;
        end else if (load) begin
            out <= in;
        end else if (inc) begin
            out <= out + 16'h0001;
        end
    end
endmodule

esc2_alu/alu.v
module alu(
    input [15:0] x,
    input [15:0] y,
    input zx,
    input nx,
    input zy,
    input ny,
    input f,
    input no,
    output [15:0] out,
    output zr,
    output ng
);
    wire [15:0] zx_out, nx_out, zy_out, ny_out, f_out, no_out;
    
    assign zx_out = zx ? 16'b0 : x;
    assign nx_out = nx ? ~zx_out : zx_out;
    
    assign zy_out = zy ? 16'b0 : y;
    assign ny_out = ny ? ~zy_out : zy_out;
    
    assign f_out = f ? (nx_out + ny_out) : (nx_out & ny_out);
    assign no_out = no ? ~f_out : f_out;
    
    assign out = no_out;
    assign zr = (no_out == 16'b0) ? 1'b1 : 1'b0;
    assign ng = no_out[15];
endmodule

T5_JoaoEmanuel/esc5/CPU.v
`timescale 1ns/1ps

/*
 * CPU Module - Hack Computer Central Processing Unit
 * 
 * The Hack CPU executes 16-bit instructions with the following format:
 * 
 * A-instruction (bit 15 = 0): 0vvvvvvvvvvvvvvv
 *   - Loads value vvvvvvvvvvvvvvv into A register
 * 
 * C-instruction (bit 15 = 1): 111a cccccc ddd jjj
 *   - a:      A/M select (0=A, 1=M[A])
 *   - cccccc: ALU control bits (zx, nx, zy, ny, f, no)
 *   - ddd:    Destination (A, D, M)
 *   - jjj:    Jump condition
 * 
 * Inputs:
 *   - inM:         Memory input (M[A])
 *   - instruction: Current instruction to execute
 *   - reset:       Reset PC to 0
 * 
 * Outputs:
 *   - outM:      Memory output (to be written to M[A])
 *   - writeM:    Memory write enable
 *   - addressM:  Memory address (A register)
 *   - pc:        Program counter
 */

module CPU(
    input  wire         clk,
    input  wire         reset,
    input  wire [15:0]  inM,          // M value input (data from memory)
    input  wire [15:0]  instruction,  // Instruction for execution
    output wire [15:0]  outM,         // M value output (data to memory)
    output wire         writeM,       // Write to M?
    output wire [14:0]  addressM,     // Address in data memory (of M)
    output wire [14:0]  pc            // Address of next instruction
);

    // Internal registers
    reg  [15:0] A;      // A register
    reg  [15:0] D;      // D register
    wire [15:0] PC_out; // Program Counter output (16-bit internally)
    
    // Instruction decode
    wire is_c_inst;     // Is C-instruction?
    wire is_a_inst;     // Is A-instruction?
    
    wire a_bit;         // A/M select
    wire [5:0] comp;    // Compute bits
    wire [2:0] dest;    // Destination bits
    wire [2:0] jump;    // Jump bits
    
    // ALU signals
    wire [15:0] alu_x, alu_y, alu_out;
    wire alu_zr, alu_ng;
    
    // Control signals
    wire load_a, load_d, load_pc;
    wire do_jump;
    wire inc_pc;
    
    // Instruction type
    assign is_c_inst = instruction[15];
    assign is_a_inst = ~instruction[15];
    
    // Decode C-instruction fields
    assign a_bit = instruction[12];
    assign comp  = instruction[11:6];  // ALU control: zx, nx, zy, ny, f, no
    assign dest  = instruction[5:3];   // d1=A, d2=D, d3=M
    assign jump  = instruction[2:0];   // j1=<0, j2==0, j3=>0
    
    // ALU inputs
    assign alu_x = D;                           // X is always D register
    assign alu_y = a_bit ? inM : A;             // Y is A or M[A] depending on a-bit
    
    // ALU instance
    alu alu_inst(
        .x(alu_x),
        .y(alu_y),
        .zx(comp[5]),
        .nx(comp[4]),
        .zy(comp[3]),
        .ny(comp[2]),
        .f(comp[1]),
        .no(comp[0]),
        .out(alu_out),
        .zr(alu_zr),
        .ng(alu_ng)
    );
    
    // Control logic for A register
    // Load A if: (1) A-instruction, or (2) C-instruction with dest[2] (d1) set
    assign load_a = is_a_inst | (is_c_inst & dest[2]);
    
    // A register
    always @(posedge clk) begin
        if (reset) begin
            A <= 16'h0000;
        end else if (load_a) begin
            if (is_a_inst)
                A <= instruction;  // A-instruction: load value
            else
                A <= alu_out;      // C-instruction: load ALU output
        end
    end
    
    // Control logic for D register
    // Load D if: C-instruction with dest[1] (d2) set
    assign load_d = is_c_inst & dest[1];
    
    // D register
    always @(posedge clk) begin
        if (reset) begin
            D <= 16'h0000;
        end else if (load_d) begin
            D <= alu_out;
        end
    end
    
    // Jump logic
    // Determine if we should jump based on ALU flags and jump bits
    wire jlt, jeq, jgt;
    assign jlt = jump[2] & alu_ng;         // j1: jump if < 0
    assign jeq = jump[1] & alu_zr;         // j2: jump if == 0
    assign jgt = jump[0] & (~alu_ng & ~alu_zr);  // j3: jump if > 0
    
    assign do_jump = is_c_inst & (jlt | jeq | jgt);
    assign inc_pc = ~do_jump;
    assign load_pc = do_jump;
    
    // Program Counter
    PC pc_inst(
        .clk(clk),
        .reset(reset),
        .load(load_pc),
        .inc(inc_pc),
        .in(A),
        .out(PC_out)
    );
    
    // Outputs
    assign outM = alu_out;                      // Data to write to memory
    assign writeM = is_c_inst & dest[0];        // Write to M if C-instruction with dest[0] (d3) set
    assign addressM = A[14:0];                  // Memory address from A register
    assign pc = PC_out[14:0];                   // Program counter (15-bit address)

endmodule

T5_JoaoEmanuel/esc5/tb_Computer.v
`timescale 1ns/1ps

/*
 * Test Bench for Computer Module
 * 
 * Tests the complete computer with three programs:
 * 1. Add.hack - Adds 2+3 and stores result in RAM[0]
 * 2. Max.hack - Computes max(RAM[0], RAM[1]) and stores in RAM[2]
 * 3. Rect.hack - Draws a rectangle on screen
 */

module tb_Computer;

    // Clock and reset
    reg clk;
    reg reset;
    
    // Instantiate Computer
    Computer uut(
        .clk(clk),
        .reset(reset)
    );
    
    // Clock generation (10ns period = 100MHz)
    initial clk = 0;
    always #5 clk = ~clk;
    
    // Task to load program into ROM
    task load_program;
        input [255:0] program_name;
        input integer num_instructions;
        integer i;
        begin
            $display("Loading program: %s (%0d instructions)", program_name, num_instructions);
            // Note: actual program loading handled in each test block
        end
    endtask
    
    // Task to display RAM contents
    task display_ram;
        input integer start_addr;
        input integer end_addr;
        integer i;
        begin
            $display("RAM contents:");
            for (i = start_addr; i <= end_addr; i = i + 1) begin
                $display("  RAM[%0d] = %0d (0x%04h)", i, 
                         $signed(uut.memory.ram.mem[i]),
                         uut.memory.ram.mem[i]);
            end
        end
    endtask
    
    // Main test
    initial begin
        $dumpfile("tb_computer.vcd");
        $dumpvars(0, tb_Computer);
        
        $display("========================================");
        $display("===== Computer Test Starting =====");
        $display("========================================");
        
        // Initialize
        reset = 1;
        #20;
        
        // ===== Test 1: Add Program =====
        // Computes 2 + 3 and stores result in RAM[0]
        begin : test1_add
            integer i;
            
            $display("\n===== TEST 1: Add Program (2 + 3) =====");
            
            // Add.hack program:
            // @2        // Load 2
            // D=A       // D = 2
            // @3        // Load 3
            // D=D+A     // D = D + 3 = 5
            // @0        // Load address 0
            // M=D       // RAM[0] = 5
            // (END)
            // @END      // Infinite loop
            // 0;JMP
            
            load_program("Add.hack", 8);
            uut.rom.mem[0] = 16'b0000000000000010;  // @2
            uut.rom.mem[1] = 16'b1110110000010000;  // D=A
            uut.rom.mem[2] = 16'b0000000000000011;  // @3
            uut.rom.mem[3] = 16'b1110000010010000;  // D=D+A
            uut.rom.mem[4] = 16'b0000000000000000;  // @0
            uut.rom.mem[5] = 16'b1110001100001000;  // M=D
            uut.rom.mem[6] = 16'b0000000000000110;  // @6 (loop)
            uut.rom.mem[7] = 16'b1110101010000111;  // 0;JMP
            
            for (i = 0; i < 8; i = i + 1) begin
                $display("  ROM[%2d] = 0x%04h", i, uut.rom.mem[i]);
            end
            
            reset = 0;
            #100;  // Run for 100ns
            
            display_ram(0, 5);
            
            if (uut.memory.ram.mem[0] == 16'd5)
                $display("  *** PASS: Add test - RAM[0] = %0d", uut.memory.ram.mem[0]);
            else
                $display("  *** FAIL: Add test - Expected RAM[0]=5, got %0d", uut.memory.ram.mem[0]);
        end
        
        #50;
        reset = 1;
        #20;
        
        // ===== Test 2: Max Program =====
        // Computes max(RAM[0], RAM[1]) and stores in RAM[2]
        begin : test2_max
            integer i;
            
            $display("\n===== TEST 2: Max Program =====");
            
            // Setup: Initialize RAM[0]=15, RAM[1]=23
            uut.memory.ram.mem[0] = 16'd15;
            uut.memory.ram.mem[1] = 16'd23;
            $display("Initial values: RAM[0]=%0d, RAM[1]=%0d", 
                     uut.memory.ram.mem[0], uut.memory.ram.mem[1]);
            
            // Max.hack program:
            // @0        // Load address 0
            // D=M       // D = RAM[0]
            // @1        // Load address 1
            // D=D-M     // D = RAM[0] - RAM[1]
            // @10       // If D > 0, goto OUTPUT_FIRST
            // D;JGT
            // @1        // Load address 1
            // D=M       // D = RAM[1] (second is larger)
            // @12       // Goto OUTPUT_D
            // 0;JMP
            // (OUTPUT_FIRST)
            // @0        // Load address 0
            // D=M       // D = RAM[0] (first is larger)
            // (OUTPUT_D)
            // @2        // Load address 2
            // M=D       // RAM[2] = D (store result)
            // (END)
            // @14       // Infinite loop
            // 0;JMP
            
            load_program("Max.hack", 16);
            uut.rom.mem[0]  = 16'b0000000000000000;  // @0
            uut.rom.mem[1]  = 16'b1111110000010000;  // D=M
            uut.rom.mem[2]  = 16'b0000000000000001;  // @1
            uut.rom.mem[3]  = 16'b1111010011010000;  // D=D-M
            uut.rom.mem[4]  = 16'b0000000000001010;  // @10
            uut.rom.mem[5]  = 16'b1110001100000001;  // D;JGT
            uut.rom.mem[6]  = 16'b0000000000000001;  // @1
            uut.rom.mem[7]  = 16'b1111110000010000;  // D=M
            uut.rom.mem[8]  = 16'b0000000000001100;  // @12
            uut.rom.mem[9]  = 16'b1110101010000111;  // 0;JMP
            uut.rom.mem[10] = 16'b0000000000000000;  // @0
            uut.rom.mem[11] = 16'b1111110000010000;  // D=M
            uut.rom.mem[12] = 16'b0000000000000010;  // @2
            uut.rom.mem[13] = 16'b1110001100001000;  // M=D
            uut.rom.mem[14] = 16'b0000000000001110;  // @14
            uut.rom.mem[15] = 16'b1110101010000111;  // 0;JMP
            
            for (i = 0; i < 16; i = i + 1) begin
                $display("  ROM[%2d] = 0x%04h", i, uut.rom.mem[i]);
            end
            
            reset = 0;
            #200;  // Run for 200ns
            
            display_ram(0, 3);
            
            if (uut.memory.ram.mem[2] == 16'd23)
                $display("  *** PASS: Max test - RAM[2] = %0d", uut.memory.ram.mem[2]);
            else
                $display("  *** FAIL: Max test - Expected RAM[2]=23, got %0d", uut.memory.ram.mem[2]);
        end
        
        #50;
        reset = 1;
        #20;
        
        // ===== Test 3: Simple Rectangle Program =====
        // Draws a small rectangle (simplified version)
        begin : test3_rect
            integer i;
            
            $display("\n===== TEST 3: Rectangle Program (Simplified) =====");
            
            // Setup: RAM[0] = number of rows to draw (e.g., 4)
            uut.memory.ram.mem[0] = 16'd4;
            $display("Drawing %0d rows", uut.memory.ram.mem[0]);
            
            // Simplified Rect program (draws RAM[0] rows of 16 pixels each)
            // @0        // n = RAM[0]
            // D=M
            // @23       // if n <= 0, goto END
            // D;JLE
            // @16384    // screen = 16384 (base address)
            // D=A
            // @addr
            // M=D       // addr = 16384
            // (LOOP)
            // @addr     // Load current screen address
            // A=M       // Set A to address
            // M=-1      // Fill 16 pixels (all black)
            // @addr
            // M=M+1     // addr = addr + 1
            // @0
            // M=M-1     // n = n - 1
            // D=M       // D = n
            // @8        // if n > 0, goto LOOP
            // D;JGT
            // (END)
            // @23       // Infinite loop
            // 0;JMP
            
            load_program("Rect.hack", 20);
            uut.rom.mem[0]  = 16'b0000000000000000;  // @0
            uut.rom.mem[1]  = 16'b1111110000010000;  // D=M
            uut.rom.mem[2]  = 16'b0000000000010111;  // @23
            uut.rom.mem[3]  = 16'b1110001100000110;  // D;JLE
            uut.rom.mem[4]  = 16'b0100000000000000;  // @16384
            uut.rom.mem[5]  = 16'b1110110000010000;  // D=A
            uut.rom.mem[6]  = 16'b0000000000010000;  // @16 (addr variable)
            uut.rom.mem[7]  = 16'b1110001100001000;  // M=D
            uut.rom.mem[8]  = 16'b0000000000010000;  // @16 (LOOP)
            uut.rom.mem[9]  = 16'b1111110000100000;  // A=M
            uut.rom.mem[10] = 16'b1110111010001000;  // M=-1
            uut.rom.mem[11] = 16'b0000000000010000;  // @16
            uut.rom.mem[12] = 16'b1111110111001000;  // M=M+1
            uut.rom.mem[13] = 16'b0000000000000000;  // @0
            uut.rom.mem[14] = 16'b1111110010001000;  // M=M-1
            uut.rom.mem[15] = 16'b1111110000010000;  // D=M
            uut.rom.mem[16] = 16'b0000000000001000;  // @8
            uut.rom.mem[17] = 16'b1110001100000001;  // D;JGT
            uut.rom.mem[18] = 16'b0000000000010111;  // @23 (END)
            uut.rom.mem[19] = 16'b1110101010000111;  // 0;JMP
            
            for (i = 0; i < 20; i = i + 1) begin
                $display("  ROM[%2d] = 0x%04h", i, uut.rom.mem[i]);
            end
            
            reset = 0;
            #500;  // Run longer for rectangle drawing
            
            $display("Screen memory (first 8 words):");
            for (integer i = 0; i < 8; i = i + 1) begin
                $display("  Screen[%0d] = 0x%04h", i, uut.memory.screen.mem[i]);
            end
            
            // Check if screen was written to
            if (uut.memory.screen.mem[0] == 16'hFFFF &&
                uut.memory.screen.mem[1] == 16'hFFFF &&
                uut.memory.screen.mem[2] == 16'hFFFF &&
                uut.memory.screen.mem[3] == 16'hFFFF)
                $display("  *** PASS: Rectangle test - Screen written correctly");
            else
                $display("  *** INFO: Rectangle test - Check screen memory above");
        end
        
        #100;
        $display("\n========================================");
        $display("===== Computer Test Complete =====");
        $display("========================================");
        $finish;
    end

endmodule

T5_JoaoEmanuel/esc5/tb_computer.vcd
$date
	Sat Feb 14 12:37:02 2026
$end
$version
	Icarus Verilog
$end
$timescale
	1ps
$end
$scope module tb_Computer $end
$var reg 1 ! clk $end
$var reg 1 " reset $end
$scope module uut $end
$var wire 1 ! clk $end
$var wire 1 " reset $end
$var wire 1 # writeM $end
$var wire 15 $ pc [14:0] $end
$var wire 16 % outM [15:0] $end
$var wire 16 & instruction [15:0] $end
$var wire 16 ' inM [15:0] $end
$var wire 15 ( addressM [14:0] $end
$scope module cpu $end
$var wire 16 ) alu_x [15:0] $end
$var wire 1 ! clk $end
$var wire 1 * do_jump $end
$var wire 1 + inc_pc $end
$var wire 1 , is_a_inst $end
$var wire 1 - jeq $end
$var wire 1 . jgt $end
$var wire 1 / jlt $end
$var wire 1 0 load_a $end
$var wire 1 1 load_d $end
$var wire 1 2 load_pc $end
$var wire 16 3 outM [15:0] $end
$var wire 1 " reset $end
$var wire 1 # writeM $end
$var wire 15 4 pc [14:0] $end
$var wire 3 5 jump [2:0] $end
$var wire 1 6 is_c_inst $end
$var wire 16 7 instruction [15:0] $end
$var wire 16 8 inM [15:0] $end
$var wire 3 9 dest [2:0] $end
$var wire 6 : comp [5:0] $end
$var wire 1 ; alu_zr $end
$var wire 16 < alu_y [15:0] $end
$var wire 16 = alu_out [15:0] $end
$var wire 1 > alu_ng $end
$var wire 15 ? addressM [14:0] $end
$var wire 1 @ a_bit $end
$var wire 16 A PC_out [15:0] $end
$var reg 16 B A [15:0] $end
$var reg 16 C D [15:0] $end
$scope module alu_inst $end
$var wire 1 D f $end
$var wire 1 E no $end
$var wire 1 F nx $end
$var wire 1 G ny $end
$var wire 16 H out [15:0] $end
$var wire 16 I x [15:0] $end
$var wire 16 J y [15:0] $end
$var wire 1 K zx $end
$var wire 1 L zy $end
$var wire 16 M zy_out [15:0] $end
$var wire 16 N zx_out [15:0] $end
$var wire 1 ; zr $end
$var wire 16 O ny_out [15:0] $end
$var wire 16 P nx_out [15:0] $end
$var wire 16 Q no_out [15:0] $end
$var wire 1 > ng $end
$var wire 16 R f_out [15:0] $end
$upscope $end
$scope module pc_inst $end
$var wire 1 ! clk $end
$var wire 16 S in [15:0] $end
$var wire 1 + inc $end
$var wire 1 2 load $end
$var wire 1 " reset $end
$var reg 16 T out [15:0] $end
$upscope $end
$upscope $end
$scope module memory $end
$var wire 15 U address [14:0] $end
$var wire 1 ! clk $end
$var wire 16 V in [15:0] $end
$var wire 1 # load $end
$var wire 1 W load_ram $end
$var wire 1 X load_screen $end
$var wire 1 Y sel_keyboard $end
$var wire 1 Z sel_ram $end
$var wire 1 [ sel_screen $end
$var wire 16 \ screen_out [15:0] $end
$var wire 16 ] ram_out [15:0] $end
$var reg 16 ^ keyboard_reg [15:0] $end
$var reg 16 _ out [15:0] $end
$scope module ram $end
$var wire 14 ` address [13:0] $end
$var wire 1 ! clk $end
$var wire 16 a in [15:0] $end
$var wire 1 W load $end
$var wire 16 b out [15:0] $end
$var parameter 32 c DEPTH $end
$var integer 32 d idx [31:0] $end
$upscope $end
$scope module screen $end
$var wire 13 e address [12:0] $end
$var wire 1 ! clk $end
$var wire 16 f in [15:0] $end
$var wire 1 X load $end
$var wire 16 g out [15:0] $end
$var parameter 32 h DEPTH $end
$var integer 32 i idx [31:0] $end
$upscope $end
$upscope $end
$scope module rom $end
$var wire 15 j address [14:0] $end
$var wire 16 k out [15:0] $end
$var parameter 32 l DEPTH $end
$var integer 32 m idx [31:0] $end
$upscope $end
$upscope $end
$scope begin test1_add $end
$var integer 32 n i [31:0] $end
$upscope $end
$scope begin test2_max $end
$var integer 32 o i [31:0] $end
$upscope $end
$scope begin test3_rect $end
$var integer 32 p i [31:0] $end
$scope begin $ivl_for_loop0 $end
$var integer 32 q i [31:0] $end
$upscope $end
$upscope $end
$scope task display_ram $end
$var integer 32 r end_addr [31:0] $end
$var integer 32 s i [31:0] $end
$var integer 32 t start_addr [31:0] $end
$upscope $end
$scope task load_program $end
$var reg 256 u program_name [255:0] $end
$var integer 32 v num_instructions [31:0] $end
$upscope $end
$upscope $end
$enddefinitions $end
$comment Show the parameter values. $end
$dumpall
b1000000000000000 l
b10000000000000 h
b100000000000000 c
$end
#0
$dumpvars
bx v
bx u
bx t
bx s
bx r
bx q
bx p
bx o
bx n
b1000000000000000 m
b0 k
b0 j
b10000000000000 i
bx g
bx f
bx e
b100000000000000 d
bx b
bx a
bx `
b0 _
b0 ^
bx ]
bx \
x[
xZ
xY
0X
0W
bx V
bx U
b0 T
bx S
bx R
bx Q
bx P
bx O
bx N
bx M
0L
0K
bx J
bx I
bx H
0G
0F
0E
0D
bx C
bx B
b0 A
0@
bx ?
x>
bx =
bx <
x;
b0 :
b0 9
b0 8
b0 7
06
b0 5
b0 4
bx 3
02
01
10
0/
0.
0-
1,
1+
0*
bx )
bx (
b0 '
b0 &
bx %
b0 $
0#
1"
0!
$end
#5000
1;
0>
b0 %
b0 3
b0 V
b0 a
b0 f
b0 =
b0 H
b0 Q
b0 R
b0 O
1Z
0[
0Y
b0 \
b0 g
b0 M
b0 ]
b0 b
b0 `
b0 e
b0 P
b0 <
b0 J
b0 (
b0 ?
b0 U
b0 N
b0 B
b0 S
b0 )
b0 C
b0 I
1!
#10000
0!
#15000
1!
#20000
1-
b10 5
b10 &
b10 7
b10 k
0!
0"
b1000 n
b1000 v
b100000101100100011001000010111001101000011000010110001101101011 u
#25000
0;
b10 %
b10 3
b10 V
b10 a
b10 f
b10 =
b10 H
b10 Q
b10 R
0-
11
b1111111111111111 P
00
1+
1K
1F
0,
02
0*
b0 5
b10 9
b110000 :
16
b10 O
b1110110000010000 &
b1110110000010000 7
b1110110000010000 k
b10 M
b10 `
b10 e
b1 $
b1 4
b1 j
b10 <
b10 J
b10 (
b10 ?
b10 U
b1 A
b1 T
b10 B
b10 S
1!
#30000
0!
#35000
0-
0;
b10 %
b10 3
b10 V
b10 a
b10 f
b10 =
b10 H
b10 Q
b10 R
1.
b10 N
b10 P
10
0K
0F
1,
01
b11 5
b0 9
b0 :
06
b11 &
b11 7
b11 k
b10 $
b10 4
b10 j
b10 )
b10 C
b10 I
b10 A
b10 T
1!
#40000
0!
#45000
b101 %
b101 3
b101 V
b101 a
b101 f
b101 =
b101 H
b101 Q
0.
11
b101 R
00
1+
1D
0,
02
0*
b0 5
b10 9
b10 :
16
b11 O
b1110000010010000 &
b1110000010010000 7
b1110000010010000 k
b11 M
b11 `
b11 e
b11 $
b11 4
b11 j
b11 <
b11 J
b11 (
b11 ?
b11 U
b11 A
b11 T
b11 B
b11 S
1!
#50000
0!
#55000
10
b1 %
b1 3
b1 V
b1 a
b1 f
b1 =
b1 H
b1 Q
0D
1,
01
b1 R
b0 9
b0 :
06
b101 P
b0 &
b0 7
b0 k
b101 N
b100 $
b100 4
b100 j
b101 )
b101 C
b101 I
b100 A
b100 T
1!
#60000
0!
#65000
0;
1W
b101 %
b101 3
b101 V
b101 a
b101 f
b101 =
b101 H
b101 Q
1#
00
b101 R
1L
1G
0,
b1 9
b1100 :
16
b1111111111111111 O
b1110001100001000 &
b1110001100001000 7
b1110001100001000 k
b0 M
b0 `
b0 e
b101 $
b101 4
b101 j
b0 <
b0 J
b0 (
b0 ?
b0 U
b101 A
b101 T
b0 B
b0 S
1!
#70000
0!
#75000
1-
1;
b0 %
b0 3
b0 V
b0 a
b0 f
b0 =
b0 H
b0 Q
b0 R
b0 O
10
0W
0L
0G
1,
0#
b110 5
b0 9
b0 :
06
b110 &
b110 7
b110 k
b101 '
b101 8
b101 _
b110 $
b110 4
b110 j
b101 ]
b101 b
b110 A
b110 T
1!
#80000
0!
#85000
0.
1-
1;
b0 P
b0 %
b0 3
b0 V
b0 a
b0 f
b0 =
b0 H
b0 Q
b0 N
00
0+
b0 R
1K
1L
1D
0,
12
1*
b111 5
b101010 :
16
b0 O
b0 '
b0 8
b0 _
b1110101010000111 &
b1110101010000111 7
b1110101010000111 k
b0 M
b0 ]
b0 b
b110 `
b110 e
b111 $
b111 4
b111 j
b110 <
b110 J
b110 (
b110 ?
b110 U
b111 A
b111 T
b110 B
b110 S
1!
#90000
0!
#95000
0-
0;
b100 %
b100 3
b100 V
b100 a
b100 f
b100 =
b100 H
b100 Q
b100 R
b101 P
b110 O
b101 N
b110 M
10
1+
0K
0L
0D
1,
02
0*
b110 5
b0 :
06
b110 &
b110 7
b110 k
b110 $
b110 4
b110 j
b110 A
b110 T
1!
#100000
0!
#105000
1-
1;
0+
12
1*
b0 P
b0 O
b0 %
b0 3
b0 V
b0 a
b0 f
b0 =
b0 H
b0 Q
0.
b0 N
b0 M
b0 R
00
1K
1L
1D
0,
b111 5
b101010 :
16
b1110101010000111 &
b1110101010000111 7
b1110101010000111 k
b111 $
b111 4
b111 j
b111 A
b111 T
1!
#110000
0!
#115000
0-
0;
b100 %
b100 3
b100 V
b100 a
b100 f
b100 =
b100 H
b100 Q
b100 R
b101 P
b110 O
b101 N
b110 M
10
1+
0K
0L
0D
1,
02
0*
b110 5
b0 :
06
b110 &
b110 7
b110 k
b110 $
b110 4
b110 j
b110 A
b110 T
1!
#120000
0!
b110 s
b101 r
b0 t
#125000
1-
1;
0+
12
1*
b0 P
b0 O
b0 %
b0 3
b0 V
b0 a
b0 f
b0 =
b0 H
b0 Q
0.
b0 N
b0 M
b0 R
00
1K
1L
1D
0,
b111 5
b101010 :
16
b1110101010000111 &
b1110101010000111 7
b1110101010000111 k
b111 $
b111 4
b111 j
b111 A
b111 T
1!
#130000
0!
#135000
0-
0;
b100 %
b100 3
b100 V
b100 a
b100 f
b100 =
b100 H
b100 Q
b100 R
b101 P
b110 O
b101 N
b110 M
10
1+
0K
0L
0D
1,
02
0*
b110 5
b0 :
06
b110 &
b110 7
b110 k
b110 $
b110 4
b110 j
b110 A
b110 T
1!
#140000
0!
#145000
1-
1;
0+
12
1*
b0 P
b0 O
b0 %
b0 3
b0 V
b0 a
b0 f
b0 =
b0 H
b0 Q
0.
b0 N
b0 M
b0 R
00
1K
1L
1D
0,
b111 5
b101010 :
16
b1110101010000111 &
b1110101010000111 7
b1110101010000111 k
b111 $
b111 4
b111 j
b111 A
b111 T
1!
#150000
0!
#155000
0-
0;
b100 %
b100 3
b100 V
b100 a
b100 f
b100 =
b100 H
b100 Q
b100 R
b101 P
b110 O
b101 N
b110 M
10
1+
0K
0L
0D
1,
02
0*
b110 5
b0 :
06
b110 &
b110 7
b110 k
b110 $
b110 4
b110 j
b110 A
b110 T
1!
#160000
0!
#165000
1-
1;
0+
12
1*
b0 P
b0 O
b0 %
b0 3
b0 V
b0 a
b0 f
b0 =
b0 H
b0 Q
0.
b0 N
b0 M
b0 R
00
1K
1L
1D
0,
b111 5
b101010 :
16
b1110101010000111 &
b1110101010000111 7
b1110101010000111 k
b111 $
b111 4
b111 j
b111 A
b111 T
1!
#170000
0!
1"
#175000
10
1+
0K
0L
0D
1,
02
0*
b101 '
b101 8
b101 _
b10 5
b0 :
06
b101 ]
b101 b
b0 `
b0 e
b10 &
b10 7
b10 k
b0 <
b0 J
b0 (
b0 ?
b0 U
b0 $
b0 4
b0 j
b0 )
b0 C
b0 I
b0 B
b0 S
b0 A
b0 T
1!
#180000
0!
#185000
1!
