T5_JoaoEmanuel/esc5/Memory.v
`timescale 1ns/1ps

/*
 * Memory Module - Hack Computer Memory System
 * 
 * Memory map:
 * 0x0000 - 0x3FFF (0-16383):     RAM16K (16K words of general-purpose RAM)
 * 0x4000 - 0x5FFF (16384-24575): Screen memory map (8K words = 256 rows x 512 pixels)
 * 0x6000 (24576):                Keyboard memory map (1 word)
 * 
 * The chip has a 15-bit address input (0-32767), but only addresses 0-24576 are used.
 */

module Memory(
    input  wire         clk,
    input  wire         load,         // Write enable
    input  wire [14:0]  address,      // 15-bit address (32K address space)
    input  wire [15:0]  in,          // Data input
    output reg  [15:0]  out          // Data output
);

    // Internal memory components
    wire [15:0] ram_out, screen_out;
    reg  [15:0] keyboard_reg;
    
    // Control signals
    wire load_ram, load_screen;
    wire sel_ram, sel_screen, sel_keyboard;
    
    // Address decoding
    // RAM:      0x0000 - 0x3FFF (address[14] = 0, address[13] = 0)
    // Screen:   0x4000 - 0x5FFF (address[14] = 1, address[13] = 0)
    // Keyboard: 0x6000          (address[14] = 1, address[13] = 1)
    
    assign sel_ram      = (~address[14]);                      // address < 16384
    assign sel_screen   = (address[14] & ~address[13]);        // 16384 <= address < 24576
    assign sel_keyboard = (address[14] & address[13]);         // address >= 24576
    
    assign load_ram     = load & sel_ram;
    assign load_screen  = load & sel_screen;
    
    // RAM16K instance (addresses 0-16383)
    RAM16K ram(
        .clk(clk),
        .load(load_ram),
        .address(address[13:0]),
        .in(in),
        .out(ram_out)
    );
    
    // Screen memory (8K words, addresses 16384-24575)
    Screen screen(
        .clk(clk),
        .load(load_screen),
        .address(address[12:0]),   // 13-bit address for 8K
        .in(in),
        .out(screen_out)
    );
    
    // Keyboard register (read-only at address 24576)
    // In simulation, this will be set by the testbench
    initial keyboard_reg = 16'h0000;
    
    // Output multiplexing
    always @(*) begin
        case ({sel_keyboard, sel_screen, sel_ram})
            3'b001: out = ram_out;
            3'b010: out = screen_out;
            3'b100: out = keyboard_reg;
            default: out = 16'h0000;
        endcase
    end

endmodule


/*
 * Screen Module - 8K words (256 rows x 512 pixels / 16 pixels per word)
 * Memory-mapped screen buffer
 */
module Screen(
    input  wire         clk,
    input  wire         load,
    input  wire [12:0]  address,      // 13-bit address (8K words)
    input  wire [15:0]  in,
    output wire [15:0]  out
);
    localparam integer DEPTH = 8192;  // 8K words
    
    reg [15:0] mem [0:DEPTH-1];
    integer idx;
    
    initial begin
        for (idx = 0; idx < DEPTH; idx = idx + 1) begin
            mem[idx] = 16'h0000;
        end
    end
    
    always @(posedge clk) begin
        if (load && address < DEPTH) begin
            mem[address] <= in;
        end
    end
    
    assign out = (address < DEPTH) ? mem[address] : 16'h0000;
endmodule

esc3/ram16k.v
`timescale 1ns/1ps

module RAM16K(
    input  wire         clk,
    input  wire         load,
    input  wire [13:0]  address,
    input  wire [15:0]  in,
    output wire [15:0]  out
);
    localparam integer DEPTH = 16384;

    reg [15:0] mem [0:DEPTH-1];
    integer idx;

    initial begin
        for (idx = 0; idx < DEPTH; idx = idx + 1) begin
            mem[idx] = 16'h0000;
        end
    end

    always @(posedge clk) begin
        if (load) begin
            mem[address] <= in;
        end
    end

    assign out = mem[address];
endmodule

T5_JoaoEmanuel/esc5/tb_Memory.v
`timescale 1ns/1ps

/*
 * Test Bench for Memory Module
 * 
 * Tests the memory system including RAM, Screen, and Keyboard regions.
 */

module tb_Memory;

    // Clock
    reg         clk;
    
    // Memory signals
    reg         load;
    reg  [14:0] address;
    reg  [15:0] in;
    wire [15:0] out;
    
    // Instantiate Memory module
    Memory uut(
        .clk(clk),
        .load(load),
        .address(address),
        .in(in),
        .out(out)
    );
    
    // Clock generation (10ns period = 100MHz)
    initial clk = 0;
    always #5 clk = ~clk;
    
    // Test stimulus
    initial begin
        $dumpfile("tb_memory.vcd");
        $dumpvars(0, tb_Memory);
        
        $display("===== Memory Test Starting =====");
        
        // Initialize
        load = 0;
        address = 0;
        in = 0;
        
        // Test 1: Write to RAM
        #10;
        $display("Test 1: Writing to RAM");
        address = 15'd100;
        in = 16'h1234;
        load = 1;
        #10;
        load = 0;
        #10;
        if (out == 16'h1234)
            $display("  PASS: Read back 0x%h from RAM[100]", out);
        else
            $display("  FAIL: Expected 0x1234, got 0x%h", out);
        
        // Test 2: Write to different RAM location
        #10;
        $display("Test 2: Writing to RAM[200]");
        address = 15'd200;
        in = 16'h5678;
        load = 1;
        #10;
        load = 0;
        #10;
        if (out == 16'h5678)
            $display("  PASS: Read back 0x%h from RAM[200]", out);
        else
            $display("  FAIL: Expected 0x5678, got 0x%h", out);
        
        // Test 3: Verify first location still holds value
        #10;
        $display("Test 3: Reading RAM[100] again");
        address = 15'd100;
        #10;
        if (out == 16'h1234)
            $display("  PASS: RAM[100] still contains 0x%h", out);
        else
            $display("  FAIL: Expected 0x1234, got 0x%h", out);
        
        // Test 4: Write to Screen memory (address 16384)
        #10;
        $display("Test 4: Writing to Screen memory");
        address = 15'd16384;  // First screen address
        in = 16'hFFFF;
        load = 1;
        #10;
        load = 0;
        #10;
        if (out == 16'hFFFF)
            $display("  PASS: Read back 0x%h from Screen[16384]", out);
        else
            $display("  FAIL: Expected 0xFFFF, got 0x%h", out);
        
        // Test 5: Write to another Screen location
        #10;
        $display("Test 5: Writing to Screen[16400]");
        address = 15'd16400;
        in = 16'hAAAA;
        load = 1;
        #10;
        load = 0;
        #10;
        if (out == 16'hAAAA)
            $display("  PASS: Read back 0x%h from Screen[16400]", out);
        else
            $display("  FAIL: Expected 0xAAAA, got 0x%h", out);
        
        // Test 6: Read from Keyboard (address 24576)
        #10;
        $display("Test 6: Reading from Keyboard");
        address = 15'd24576;
        #10;
        $display("  INFO: Keyboard value = 0x%h (should be 0 by default)", out);
        
        // Test 7: Verify address ranges don't overlap
        #10;
        $display("Test 7: Verifying RAM and Screen are separate");
        address = 15'd100;
        #10;
        if (out == 16'h1234)
            $display("  PASS: RAM[100] still contains 0x%h", out);
        else
            $display("  FAIL: RAM corrupted, got 0x%h", out);
        
        #10;
        address = 15'd16384;
        #10;
        if (out == 16'hFFFF)
            $display("  PASS: Screen[16384] still contains 0x%h", out);
        else
            $display("  FAIL: Screen corrupted, got 0x%h", out);
        
        #50;
        $display("===== Memory Test Complete =====");
        $finish;
    end

endmodule

T5_JoaoEmanuel/esc5/tb_memory.vcd
$date
	Sat Feb 14 12:37:02 2026
$end
$version
	Icarus Verilog
$end
$timescale
	1ps
$end
$scope module tb_Memory $end
$var wire 16 ! out [15:0] $end
$var reg 15 " address [14:0] $end
$var reg 1 # clk $end
$var reg 16 $ in [15:0] $end
$var reg 1 % load $end
$scope module uut $end
$var wire 15 & address [14:0] $end
$var wire 1 # clk $end
$var wire 16 ' in [15:0] $end
$var wire 1 % load $end
$var wire 1 ( load_ram $end
$var wire 1 ) load_screen $end
$var wire 1 * sel_keyboard $end
$var wire 1 + sel_ram $end
$var wire 1 , sel_screen $end
$var wire 16 - screen_out [15:0] $end
$var wire 16 . ram_out [15:0] $end
$var reg 16 / keyboard_reg [15:0] $end
$var reg 16 0 out [15:0] $end
$scope module ram $end
$var wire 14 1 address [13:0] $end
$var wire 1 # clk $end
$var wire 16 2 in [15:0] $end
$var wire 1 ( load $end
$var wire 16 3 out [15:0] $end
$var parameter 32 4 DEPTH $end
$var integer 32 5 idx [31:0] $end
$upscope $end
$scope module screen $end
$var wire 13 6 address [12:0] $end
$var wire 1 # clk $end
$var wire 16 7 in [15:0] $end
$var wire 1 ) load $end
$var wire 16 8 out [15:0] $end
$var parameter 32 9 DEPTH $end
$var integer 32 : idx [31:0] $end
$upscope $end
$upscope $end
$upscope $end
$enddefinitions $end
$comment Show the parameter values. $end
$dumpall
b10000000000000 9
b100000000000000 4
$end
#0
$dumpvars
b10000000000000 :
b0 8
b0 7
b0 6
b100000000000000 5
b0 3
b0 2
b0 1
b0 0
b0 /
b0 .
b0 -
0,
1+
0*
0)
0(
b0 '
b0 &
0%
b0 $
0#
b0 "
b0 !
$end
#5000
1#
#10000
1(
b1100100 1
b1100100 6
0#
1%
b1001000110100 $
b1001000110100 '
b1001000110100 2
b1001000110100 7
b1100100 "
b1100100 &
#15000
b1001000110100 !
b1001000110100 0
b1001000110100 .
b1001000110100 3
1#
#20000
0(
0#
0%
#25000
1#
#30000
0#
#35000
1#
#40000
b0 !
b0 0
1(
b0 .
b0 3
b11001000 1
b11001000 6
0#
1%
b101011001111000 $
b101011001111000 '
b101011001111000 2
b101011001111000 7
b11001000 "
b11001000 &
#45000
b101011001111000 !
b101011001111000 0
b101011001111000 .
b101011001111000 3
1#
#50000
0(
0#
0%
#55000
1#
#60000
0#
#65000
1#
#70000
b1001000110100 !
b1001000110100 0
b1001000110100 .
b1001000110100 3
b1100100 1
b1100100 6
0#
b1100100 "
b1100100 &
#75000
1#
#80000
0#
#85000
1#
#90000
1)
0+
1,
b0 !
b0 0
0(
b0 .
b0 3
b0 1
b0 6
0#
1%
b1111111111111111 $
b1111111111111111 '
b1111111111111111 2
b1111111111111111 7
b100000000000000 "
b100000000000000 &
#95000
b1111111111111111 !
b1111111111111111 0
b1111111111111111 -
b1111111111111111 8
1#
#100000
0)
0#
0%
#105000
1#
#110000
0#
#115000
1#
#120000
b0 !
b0 0
b0 -
b0 8
1)
b10000 1
b10000 6
0#
1%
b1010101010101010 $
b1010101010101010 '
b1010101010101010 2
b1010101010101010 7
b100000000010000 "
b100000000010000 &
#125000
b1010101010101010 !
b1010101010101010 0
b1010101010101010 -
b1010101010101010 8
1#
#130000
0)
0#
0%
#135000
1#
#140000
0#
#145000
1#
#150000
0,
b0 !
b0 0
1*
b1111111111111111 -
b1111111111111111 8
b10000000000000 1
b0 6
0#
b110000000000000 "
b110000000000000 &
#155000
1#
#160000
0#
#165000
1#
#170000
b1001000110100 !
b1001000110100 0
1+
0*
b0 -
b0 8
b1001000110100 .
b1001000110100 3
b1100100 1
b1100100 6
0#
b1100100 "
b1100100 &
#175000
1#
#180000
0#
#185000
1#
#190000
0+
1,
b1111111111111111 !
b1111111111111111 0
b1111111111111111 -
b1111111111111111 8
b0 .
b0 3
b0 1
b0 6
0#
b100000000000000 "
b100000000000000 &
